simpleenvs/__init__.py
simpleenvs/envs/__init__.py
simpleenvs/envs/continuous_rooms/__init__.py
simpleenvs/envs/continuous_rooms/rooms.py
simpleenvs/envs/continuous_rooms/data/__init__.py
simpleenvs/envs/continuous_rooms/data/empty_room.txt
simpleenvs/envs/continuous_rooms/data/snake_room.txt
simpleenvs/envs/continuous_rooms/data/xu_four_rooms.txt
simpleenvs/envs/discrete_rooms/__init__.py
simpleenvs/envs/discrete_rooms/explorable_rooms.py
simpleenvs/envs/discrete_rooms/extra_items_rooms.py
simpleenvs/envs/discrete_rooms/rooms.py
simpleenvs/envs/discrete_rooms/data/__init__.py
simpleenvs/envs/discrete_rooms/data/bridge_room.txt
simpleenvs/envs/discrete_rooms/data/cage_room.txt
simpleenvs/envs/discrete_rooms/data/empty_room.txt
simpleenvs/envs/discrete_rooms/data/four_rooms.txt
simpleenvs/envs/discrete_rooms/data/four_rooms_holes.txt
simpleenvs/envs/discrete_rooms/data/maze_rooms.txt
simpleenvs/envs/discrete_rooms/data/nine_rooms.txt
simpleenvs/envs/discrete_rooms/data/parr_maze.txt
simpleenvs/envs/discrete_rooms/data/parr_mini_maze.txt
simpleenvs/envs/discrete_rooms/data/ramesh_maze.txt
simpleenvs/envs/discrete_rooms/data/six_rooms.txt
simpleenvs/envs/discrete_rooms/data/small_rooms.txt
simpleenvs/envs/discrete_rooms/data/snake_room.txt
simpleenvs/envs/discrete_rooms/data/spiral_room.txt
simpleenvs/envs/discrete_rooms/data/two_rooms.txt
simpleenvs/envs/discrete_rooms/data/xu_four_rooms.txt
simpleenvs/envs/hanoi/__init__.py
simpleenvs/envs/hanoi/explorable_hanoi.py
simpleenvs/envs/hanoi/hanoi.py
simpleenvs/envs/playroom/__init__.py
simpleenvs/envs/playroom/playroom.py
simpleenvs/envs/taxi/__init__.py
simpleenvs/envs/taxi/taxi.py
simpleenvs/renderers/__init__.py
simpleenvs/renderers/hanoi_renderer.py
simpleenvs/renderers/room_renderer.py
simpleenvs/renderers/taxi_renderer.py
simpleenvs/renderers/taxi_renderer_resources/__init__.py
simpleenvs/renderers/taxi_renderer_resources/goal_flag.png
simpleenvs/renderers/taxi_renderer_resources/passenger.png
simpleenvs-0.6.2.dist-info/LICENSE
simpleenvs-0.6.2.dist-info/METADATA
simpleenvs-0.6.2.dist-info/WHEEL
simpleenvs-0.6.2.dist-info/top_level.txt
simpleenvs-0.6.2.dist-info/RECORD
