Metadata-Version: 2.2
Name: simpleenvs
Version: 0.6.2
Summary: Implementations of various sequential decision problems as MDPs using the SimpleOptions framework.
Author-email: Joshua Evans <jbe25@bath.ac.uk>
License: MIT License
Project-URL: homepage, https://github.com/Ueva/BaRL_Envs
Classifier: Programming Language :: Python :: 3
Classifier: Programming Language :: Python :: 3.11
Classifier: Programming Language :: Python :: 3.12
Classifier: License :: OSI Approved :: MIT License
Classifier: Operating System :: OS Independent
Classifier: Intended Audience :: Science/Research
Classifier: Topic :: Scientific/Engineering :: Artificial Intelligence
Classifier: Natural Language :: English
Requires-Python: >=3.11
License-File: LICENSE
Requires-Dist: simpleoptions
Requires-Dist: importlib_resources
Requires-Dist: importlib_metadata
Requires-Dist: numpy
Requires-Dist: networkx
Requires-Dist: pygame
Requires-Dist: gymnasium
Requires-Dist: distinctipy
